strictly.py
strictly-1.1.2.dist-info/LICENSE
strictly-1.1.2.dist-info/METADATA
strictly-1.1.2.dist-info/WHEEL
strictly-1.1.2.dist-info/top_level.txt
strictly-1.1.2.dist-info/RECORD
