Metadata-Version: 2.1
Name: strictly
Version: 1.1.2
Summary: A run-time tool to enforce strict typing in python using type hints
Home-page: https://github.com/TG-Techie/strictly
Author: Jonah Yolles-Murphy
Author-email: jonahym@mitre.org
License: UNKNOWN
Platform: UNKNOWN
Classifier: Programming Language :: Python :: 3
Classifier: License :: OSI Approved :: MIT License
Classifier: Operating System :: OS Independent
Requires-Python: >=3.7
